observe/__init__.py
observe/logger.py
observe/trace.py
y_observe-0.1.8.dist-info/METADATA
y_observe-0.1.8.dist-info/WHEEL
y_observe-0.1.8.dist-info/RECORD
